cvesearch/__init__.py
cvesearch/cvesearch.py
cvesearch-1.2.dist-info/DESCRIPTION.rst
cvesearch-1.2.dist-info/METADATA
cvesearch-1.2.dist-info/RECORD
cvesearch-1.2.dist-info/WHEEL
cvesearch-1.2.dist-info/dependency_links.txt
cvesearch-1.2.dist-info/entry_points.txt
cvesearch-1.2.dist-info/metadata.json
cvesearch-1.2.dist-info/top_level.txt
