Metadata-Version: 2.0
Name: cvesearch
Version: 1.2
Summary: Search references, exploit modules and pocs for any CVE ID
Home-page: https://pypi.org/project/cvesearch/
Author: Sujit Ghosal
Author-email: thesujit@gmail.com
License: UNKNOWN
Keywords: cve cveid cvesearch cvelinks cvepoc cveurl vulnerability exploits references poc search
Platform: UNKNOWN
Classifier: Programming Language :: Python :: 3
Classifier: License :: OSI Approved :: MIT License
Classifier: Operating System :: OS Independent
Requires-Python: >=3
Requires-Dist: termcolor
Requires-Dist: requests
Requires-Dist: ujson
